lpcdaskgateway/__init__.py
lpcdaskgateway/cluster.py
lpcdaskgateway/gateway.py
lpcdaskgateway-0.1.4.dist-info/METADATA
lpcdaskgateway-0.1.4.dist-info/WHEEL
lpcdaskgateway-0.1.4.dist-info/top_level.txt
lpcdaskgateway-0.1.4.dist-info/RECORD
