Metadata-Version: 2.1
Name: lpcdaskgateway
Version: 0.1.4
Summary: Launches a Dask Gateway cluster in K8s and joins HTCondor workers to it
Home-page: https://github.com/mapsacosta/lpcdaskgateway
Author: Maria P. Acosta F./Fermilab EAF project
Author-email: macosta@fnal.gov
License: Apache
Platform: UNKNOWN
Classifier: Programming Language :: Python :: 3
Classifier: License :: OSI Approved :: MIT License
Classifier: Operating System :: OS Independent
Requires-Python: >=3.8
